setup.py
forcastweather/__init__.py
forcastweather/forcastweather.py
forcastweather.egg-info/PKG-INFO
forcastweather.egg-info/SOURCES.txt
forcastweather.egg-info/dependency_links.txt
forcastweather.egg-info/requires.txt
forcastweather.egg-info/top_level.txt